{"meta":{"version":"2025-09-09","jis_muni_code":"13103","ward":"港区"},"data":{"芝|1":{"lat":35.651263,"lng":139.75466,"level":"chome"},"芝|2":{"lat":35.651524,"lng":139.751704,"level":"chome"},"芝|3":{"lat":35.651923,"lng":139.747044,"level":"chome"},"芝|4":{"lat":35.648505,"lng":139.750601,"level":"chome"},"芝|5":{"lat":35.647609,"lng":139.746512,"level":"chome"},"海岸|1":{"lat":35.655391,"lng":139.760198,"level":"chome"},"海岸|2":{"lat":35.64906,"lng":139.758981,"level":"chome"},"海岸|3":{"lat":35.640866,"lng":139.756761,"level":"chome"},"東新橋|1":{"lat":35.663334,"lng":139.760503,"level":"chome"},"東新橋|2":{"lat":35.661439,"lng":139.757285,"level":"chome"},"新橋|1":{"lat":35.667925,"lng":139.758539,"level":"chome"},"新橋|2":{"lat":35.666875,"lng":139.757259,"level":"chome"},"新橋|3":{"lat":35.665606,"lng":139.756279,"level":"chome"},"新橋|4":{"lat":35.664426,"lng":139.755801,"level":"chome"},"新橋|5":{"lat":35.663126,"lng":139.754812,"level":"chome"},"新橋|6":{"lat":35.66148,"lng":139.753726,"level":"chome"},"西新橋|1":{"lat":35.66882,"lng":139.753121,"level":"chome"},"西新橋|2":{"lat":35.666327,"lng":139.751991,"level":"chome"},"西新橋|3":{"lat":35.663379,"lng":139.750949,"level":"chome"},"三田|1":{"lat":35.653612,"lng":139.741145,"level":"chome"},"三田|2":{"lat":35.649996,"lng":139.741064,"level":"chome"},"三田|3":{"lat":35.643816,"lng":139.742483,"level":"chome"},"三田|4":{"lat":35.643769,"lng":139.739608,"level":"chome"},"三田|5":{"lat":35.646296,"lng":139.73782,"level":"chome"},"浜松町|1":{"lat":35.658404,"lng":139.756364,"level":"chome"},"浜松町|2":{"lat":35.654926,"lng":139.755681,"level":"chome"},"芝大門|1":{"lat":35.65875,"lng":139.753844,"level":"chome"},"芝大門|2":{"lat":35.655128,"lng":139.753663,"level":"chome"},"芝公園|1":{"lat":35.658761,"lng":139.75163,"level":"chome"},"芝公園|2":{"lat":35.655251,"lng":139.751352,"level":"chome"},"芝公園|3":{"lat":35.660047,"lng":139.74762,"level":"chome"},"芝公園|4":{"lat":35.656231,"lng":139.747321,"level":"chome"},"虎ノ門|1":{"lat":35.668608,"lng":139.749483,"level":"chome"},"虎ノ門|2":{"lat":35.668239,"lng":139.745703,"level":"chome"},"虎ノ門|3":{"lat":35.664423,"lng":139.74683,"level":"chome"},"虎ノ門|4":{"lat":35.664791,"lng":139.744217,"level":"chome"},"虎ノ門|5":{"lat":35.662614,"lng":139.743589,"level":"chome"},"愛宕|1":{"lat":35.665132,"lng":139.7489,"level":"chome"},"愛宕|2":{"lat":35.662888,"lng":139.748463,"level":"chome"},"麻布狸穴町|-":{"lat":35.659034,"lng":139.739443,"level":"town"},"麻布永坂町|-":{"lat":35.658561,"lng":139.737635,"level":"town"},"南麻布|1":{"lat":35.65115,"lng":139.734252,"level":"chome"},"南麻布|2":{"lat":35.648355,"lng":139.73525,"level":"chome"},"南麻布|3":{"lat":35.649252,"lng":139.730304,"level":"chome"},"南麻布|4":{"lat":35.648851,"lng":139.725676,"level":"chome"},"南麻布|5":{"lat":35.653046,"lng":139.724724,"level":"chome"},"元麻布|1":{"lat":35.653817,"lng":139.732611,"level":"chome"},"元麻布|2":{"lat":35.654184,"lng":139.729126,"level":"chome"},"元麻布|3":{"lat":35.656712,"lng":139.729566,"level":"chome"},"西麻布|1":{"lat":35.661262,"lng":139.725311,"level":"chome"},"西麻布|2":{"lat":35.6611,"lng":139.720495,"level":"chome"},"西麻布|3":{"lat":35.658029,"lng":139.725653,"level":"chome"},"西麻布|4":{"lat":35.657805,"lng":139.72135,"level":"chome"},"六本木|1":{"lat":35.66485,"lng":139.740724,"level":"chome"},"六本木|2":{"lat":35.667035,"lng":139.737278,"level":"chome"},"六本木|3":{"lat":35.663724,"lng":139.736535,"level":"chome"},"六本木|4":{"lat":35.665117,"lng":139.733758,"level":"chome"},"六本木|5":{"lat":35.659853,"lng":139.734565,"level":"chome"},"六本木|6":{"lat":35.660083,"lng":139.730518,"level":"chome"},"六本木|7":{"lat":35.664023,"lng":139.727539,"level":"chome"},"麻布台|1":{"lat":35.661294,"lng":139.740806,"level":"chome"},"麻布台|2":{"lat":35.658868,"lng":139.741678,"level":"chome"},"麻布台|3":{"lat":35.660205,"lng":139.738277,"level":"chome"},"麻布十番|1":{"lat":35.656657,"lng":139.735186,"level":"chome"},"麻布十番|2":{"lat":35.655027,"lng":139.735169,"level":"chome"},"麻布十番|3":{"lat":35.653194,"lng":139.735406,"level":"chome"},"麻布十番|4":{"lat":35.654093,"lng":139.737221,"level":"chome"},"東麻布|1":{"lat":35.656368,"lng":139.743725,"level":"chome"},"東麻布|2":{"lat":35.656761,"lng":139.740852,"level":"chome"},"東麻布|3":{"lat":35.656669,"lng":139.738041,"level":"chome"},"元赤坂|1":{"lat":35.67778,"lng":139.734143,"level":"chome"},"元赤坂|2":{"lat":35.677531,"lng":139.727344,"level":"chome"},"赤坂|1":{"lat":35.668753,"lng":139.742492,"level":"chome"},"赤坂|2":{"lat":35.670926,"lng":139.739594,"level":"chome"},"赤坂|3":{"lat":35.675402,"lng":139.737085,"level":"chome"},"赤坂|4":{"lat":35.674662,"lng":139.733565,"level":"chome"},"赤坂|5":{"lat":35.672379,"lng":139.734745,"level":"chome"},"赤坂|6":{"lat":35.669226,"lng":139.735356,"level":"chome"},"赤坂|7":{"lat":35.671886,"lng":139.730725,"level":"chome"},"赤坂|8":{"lat":35.670619,"lng":139.728245,"level":"chome"},"赤坂|9":{"lat":35.666924,"lng":139.730631,"level":"chome"},"南青山|1":{"lat":35.669416,"lng":139.72547,"level":"chome"},"南青山|2":{"lat":35.667675,"lng":139.721464,"level":"chome"},"南青山|3":{"lat":35.666349,"lng":139.715353,"level":"chome"},"南青山|4":{"lat":35.664736,"lng":139.718064,"level":"chome"},"南青山|5":{"lat":35.662487,"lng":139.7133,"level":"chome"},"南青山|6":{"lat":35.660464,"lng":139.716353,"level":"chome"},"南青山|7":{"lat":35.657971,"lng":139.716342,"level":"chome"},"北青山|1":{"lat":35.674841,"lng":139.721293,"level":"chome"},"北青山|2":{"lat":35.671916,"lng":139.717552,"level":"chome"},"北青山|3":{"lat":35.66629,"lng":139.712363,"level":"chome"},"高輪|1":{"lat":35.640288,"lng":139.734466,"level":"chome"},"高輪|2":{"lat":35.637249,"lng":139.73768,"level":"chome"},"高輪|3":{"lat":35.632148,"lng":139.734774,"level":"chome"},"高輪|4":{"lat":35.626791,"lng":139.734863,"level":"chome"},"白金|1":{"lat":35.645173,"lng":139.7334,"level":"chome"},"白金|2":{"lat":35.641675,"lng":139.731103,"level":"chome"},"白金|3":{"lat":35.645375,"lng":139.729819,"level":"chome"},"白金|4":{"lat":35.64235,"lng":139.72731,"level":"chome"},"白金|5":{"lat":35.645405,"lng":139.725619,"level":"chome"},"白金|6":{"lat":35.643192,"lng":139.723456,"level":"chome"},"白金台|1":{"lat":35.638125,"lng":139.730102,"level":"chome"},"白金台|2":{"lat":35.633747,"lng":139.729211,"level":"chome"},"白金台|3":{"lat":35.636121,"lng":139.725692,"level":"chome"},"白金台|4":{"lat":35.639433,"lng":139.725,"level":"chome"},"白金台|5":{"lat":35.638597,"lng":139.720205,"level":"chome"},"芝浦|1":{"lat":35.648672,"lng":139.754744,"level":"chome"},"芝浦|2":{"lat":35.644081,"lng":139.753209,"level":"chome"},"芝浦|3":{"lat":35.643885,"lng":139.748395,"level":"chome"},"芝浦|4":{"lat":35.639717,"lng":139.747026,"level":"chome"},"港南|1":{"lat":35.633372,"lng":139.744291,"level":"chome"},"港南|2":{"lat":35.629377,"lng":139.741612,"level":"chome"},"港南|3":{"lat":35.633293,"lng":139.749969,"level":"chome"},"港南|4":{"lat":35.628158,"lng":139.74907,"level":"chome"},"港南|5":{"lat":35.629066,"lng":139.756318,"level":"chome"},"台場|1":{"lat":35.630964,"lng":139.778506,"level":"chome"},"台場|2":{"lat":35.627522,"lng":139.775796,"level":"chome"},"‐|-":{"lat":35.636571,"lng":139.749685,"level":"town"},"__CITY__|-|-":{"lat":35.652627264285705,"lng":139.74178237142857,"level":"city"}}}