{"meta":{"version":"2025-10-16","jis_muni_code":"13121","name":"足立区"},"data":{"青井|1":{"lat":35.773903,"lng":139.812454,"level":"chome"},"青井|2":{"lat":35.772041,"lng":139.81431,"level":"chome"},"青井|3":{"lat":35.771666,"lng":139.819623,"level":"chome"},"青井|4":{"lat":35.775113,"lng":139.81991,"level":"chome"},"青井|5":{"lat":35.777289,"lng":139.819409,"level":"chome"},"青井|6":{"lat":35.77696,"lng":139.813461,"level":"chome"},"足立|1":{"lat":35.762609,"lng":139.805939,"level":"chome"},"足立|2":{"lat":35.760234,"lng":139.811114,"level":"chome"},"足立|3":{"lat":35.763573,"lng":139.810422,"level":"chome"},"足立|4":{"lat":35.766326,"lng":139.805873,"level":"chome"},"綾瀬|1":{"lat":35.75892,"lng":139.821999,"level":"chome"},"綾瀬|2":{"lat":35.759977,"lng":139.828312,"level":"chome"},"綾瀬|3":{"lat":35.764251,"lng":139.826489,"level":"chome"},"綾瀬|4":{"lat":35.765071,"lng":139.822392,"level":"chome"},"綾瀬|5":{"lat":35.767491,"lng":139.826805,"level":"chome"},"綾瀬|6":{"lat":35.770588,"lng":139.825835,"level":"chome"},"綾瀬|7":{"lat":35.773677,"lng":139.826394,"level":"chome"},"伊興|1":{"lat":35.790075,"lng":139.784885,"level":"chome"},"伊興|2":{"lat":35.79271,"lng":139.781092,"level":"chome"},"伊興|3":{"lat":35.793885,"lng":139.78537,"level":"chome"},"伊興|4":{"lat":35.796613,"lng":139.783786,"level":"chome"},"伊興|5":{"lat":35.798969,"lng":139.782047,"level":"chome"},"入谷町，舎人町|-":{"lat":35.800229,"lng":139.770568,"level":"town"},"入谷|1":{"lat":35.803776,"lng":139.768163,"level":"chome"},"入谷|2":{"lat":35.808305,"lng":139.765039,"level":"chome"},"入谷|3":{"lat":35.810183,"lng":139.760782,"level":"chome"},"入谷|4":{"lat":35.80657,"lng":139.761058,"level":"chome"},"入谷|5":{"lat":35.803397,"lng":139.762739,"level":"chome"},"入谷|6":{"lat":35.799497,"lng":139.76526,"level":"chome"},"入谷|7":{"lat":35.799916,"lng":139.760207,"level":"chome"},"入谷|8":{"lat":35.805125,"lng":139.756775,"level":"chome"},"入谷|9":{"lat":35.808928,"lng":139.754531,"level":"chome"},"梅田|1":{"lat":35.763133,"lng":139.801377,"level":"chome"},"梅田|2":{"lat":35.765832,"lng":139.801719,"level":"chome"},"梅田|3":{"lat":35.763985,"lng":139.796906,"level":"chome"},"梅田|4":{"lat":35.763953,"lng":139.793186,"level":"chome"},"梅田|5":{"lat":35.769301,"lng":139.793888,"level":"chome"},"梅田|6":{"lat":35.767885,"lng":139.797396,"level":"chome"},"梅田|7":{"lat":35.769466,"lng":139.800335,"level":"chome"},"梅田|8":{"lat":35.772805,"lng":139.795151,"level":"chome"},"梅島|1":{"lat":35.7728,"lng":139.800927,"level":"chome"},"梅島|2":{"lat":35.776653,"lng":139.800565,"level":"chome"},"梅島|3":{"lat":35.77636,"lng":139.794771,"level":"chome"},"扇|1":{"lat":35.763264,"lng":139.774563,"level":"chome"},"扇|2":{"lat":35.764157,"lng":139.768271,"level":"chome"},"扇|3":{"lat":35.770662,"lng":139.772445,"level":"chome"},"大谷田|1":{"lat":35.778753,"lng":139.846242,"level":"chome"},"大谷田|2":{"lat":35.782316,"lng":139.845116,"level":"chome"},"大谷田|3":{"lat":35.778831,"lng":139.841305,"level":"chome"},"大谷田|4":{"lat":35.779229,"lng":139.837992,"level":"chome"},"大谷田|5":{"lat":35.783401,"lng":139.839613,"level":"chome"},"興野|1":{"lat":35.769598,"lng":139.782364,"level":"chome"},"興野|2":{"lat":35.768922,"lng":139.777273,"level":"chome"},"小台|1":{"lat":35.755035,"lng":139.769761,"level":"chome"},"小台|2":{"lat":35.757156,"lng":139.759627,"level":"chome"},"加賀|1":{"lat":35.788883,"lng":139.759309,"level":"chome"},"加賀|2":{"lat":35.792287,"lng":139.759514,"level":"chome"},"加平|1":{"lat":35.776197,"lng":139.827415,"level":"chome"},"加平|2":{"lat":35.780189,"lng":139.826397,"level":"chome"},"加平|3":{"lat":35.780024,"lng":139.829055,"level":"chome"},"北加平町|-":{"lat":35.784258,"lng":139.828759,"level":"town"},"栗原|1":{"lat":35.780421,"lng":139.789663,"level":"chome"},"栗原|2":{"lat":35.78383,"lng":139.789294,"level":"chome"},"栗原|3":{"lat":35.779925,"lng":139.785434,"level":"chome"},"栗原|4":{"lat":35.785396,"lng":139.785658,"level":"chome"},"江北|1":{"lat":35.769174,"lng":139.768167,"level":"chome"},"江北|2":{"lat":35.768679,"lng":139.763806,"level":"chome"},"江北|3":{"lat":35.774668,"lng":139.761833,"level":"chome"},"江北|4":{"lat":35.77365,"lng":139.76662,"level":"chome"},"江北|5":{"lat":35.776958,"lng":139.767587,"level":"chome"},"江北|6":{"lat":35.780611,"lng":139.767657,"level":"chome"},"江北|7":{"lat":35.780759,"lng":139.763321,"level":"chome"},"古千谷|1":{"lat":35.797018,"lng":139.772623,"level":"chome"},"古千谷|2":{"lat":35.800461,"lng":139.773659,"level":"chome"},"弘道|1":{"lat":35.768379,"lng":139.812137,"level":"chome"},"弘道|2":{"lat":35.76842,"lng":139.81754,"level":"chome"},"佐野|1":{"lat":35.787139,"lng":139.843476,"level":"chome"},"佐野|2":{"lat":35.787349,"lng":139.838539,"level":"chome"},"皿沼|1":{"lat":35.792986,"lng":139.763055,"level":"chome"},"皿沼|2":{"lat":35.791512,"lng":139.767441,"level":"chome"},"皿沼|3":{"lat":35.794335,"lng":139.766966,"level":"chome"},"鹿浜|1":{"lat":35.777394,"lng":139.751334,"level":"chome"},"鹿浜|2":{"lat":35.769601,"lng":139.759867,"level":"chome"},"鹿浜|3":{"lat":35.781054,"lng":139.753461,"level":"chome"},"鹿浜|4":{"lat":35.781702,"lng":139.758089,"level":"chome"},"鹿浜|5":{"lat":35.78576,"lng":139.753329,"level":"chome"},"鹿浜|6":{"lat":35.785914,"lng":139.759341,"level":"chome"},"鹿浜|7":{"lat":35.784683,"lng":139.763338,"level":"chome"},"鹿浜|8":{"lat":35.78821,"lng":139.763699,"level":"chome"},"島根|1":{"lat":35.779541,"lng":139.799986,"level":"chome"},"島根|2":{"lat":35.782632,"lng":139.800602,"level":"chome"},"島根|3":{"lat":35.779816,"lng":139.794631,"level":"chome"},"島根|4":{"lat":35.782977,"lng":139.794619,"level":"chome"},"神明南|1":{"lat":35.788614,"lng":139.829117,"level":"chome"},"神明南|2":{"lat":35.789083,"lng":139.832114,"level":"chome"},"神明|1":{"lat":35.792862,"lng":139.829379,"level":"chome"},"神明|2":{"lat":35.793911,"lng":139.83467,"level":"chome"},"神明|3":{"lat":35.797369,"lng":139.835587,"level":"chome"},"新田|1":{"lat":35.774494,"lng":139.74428,"level":"chome"},"新田|2":{"lat":35.771765,"lng":139.740586,"level":"chome"},"新田|3":{"lat":35.769573,"lng":139.746858,"level":"chome"},"千住曙町|-":{"lat":35.74239,"lng":139.814088,"level":"town"},"千住旭町|-":{"lat":35.749271,"lng":139.807087,"level":"town"},"千住東|1":{"lat":35.744538,"lng":139.805177,"level":"chome"},"千住東|2":{"lat":35.745552,"lng":139.808289,"level":"chome"},"千住大川町|-":{"lat":35.756299,"lng":139.798079,"level":"town"},"千住河原町|-":{"lat":35.742962,"lng":139.798934,"level":"town"},"関原|1":{"lat":35.763125,"lng":139.789176,"level":"chome"},"関原|2":{"lat":35.767345,"lng":139.789062,"level":"chome"},"関原|3":{"lat":35.771316,"lng":139.788357,"level":"chome"},"千住寿町|-":{"lat":35.753292,"lng":139.799326,"level":"town"},"千住桜木|1":{"lat":35.751325,"lng":139.792014,"level":"chome"},"千住桜木|2":{"lat":35.754557,"lng":139.787092,"level":"chome"},"千住関屋町|-":{"lat":35.741544,"lng":139.806012,"level":"town"},"千住龍田町|-":{"lat":35.751656,"lng":139.795233,"level":"town"},"千住橋戸町|-":{"lat":35.740796,"lng":139.797465,"level":"town"},"千住宮元町|-":{"lat":35.747147,"lng":139.796112,"level":"town"},"千住緑町|1":{"lat":35.743055,"lng":139.792082,"level":"chome"},"千住緑町|2":{"lat":35.745321,"lng":139.792277,"level":"chome"},"千住緑町|3":{"lat":35.747414,"lng":139.791892,"level":"chome"},"千住元町|-":{"lat":35.755181,"lng":139.792671,"level":"town"},"千住柳町|-":{"lat":35.7541,"lng":139.796485,"level":"town"},"千住中居町|-":{"lat":35.749583,"lng":139.79793,"level":"town"},"千住仲町|-":{"lat":35.745225,"lng":139.800839,"level":"town"},"千住|1":{"lat":35.747754,"lng":139.801183,"level":"chome"},"千住|2":{"lat":35.749672,"lng":139.802065,"level":"chome"},"千住|3":{"lat":35.751648,"lng":139.802667,"level":"chome"},"千住|4":{"lat":35.753535,"lng":139.803541,"level":"chome"},"千住|5":{"lat":35.755298,"lng":139.804352,"level":"chome"},"竹の塚|1":{"lat":35.790484,"lng":139.791542,"level":"chome"},"竹の塚|2":{"lat":35.790593,"lng":139.795861,"level":"chome"},"竹の塚|3":{"lat":35.790714,"lng":139.800193,"level":"chome"},"竹の塚|4":{"lat":35.793831,"lng":139.800092,"level":"chome"},"竹の塚|5":{"lat":35.795565,"lng":139.796158,"level":"chome"},"竹の塚|6":{"lat":35.79557,"lng":139.793042,"level":"chome"},"竹の塚|7":{"lat":35.799714,"lng":139.795145,"level":"chome"},"辰沼|1":{"lat":35.785373,"lng":139.835042,"level":"chome"},"辰沼|2":{"lat":35.789762,"lng":139.834645,"level":"chome"},"中央本町|1":{"lat":35.773102,"lng":139.804533,"level":"chome"},"中央本町|2":{"lat":35.769244,"lng":139.807818,"level":"chome"},"中央本町|3":{"lat":35.772402,"lng":139.808159,"level":"chome"},"中央本町|4":{"lat":35.775416,"lng":139.80835,"level":"chome"},"中央本町|5":{"lat":35.777864,"lng":139.807207,"level":"chome"},"椿|1":{"lat":35.77769,"lng":139.759077,"level":"chome"},"椿|2":{"lat":35.779541,"lng":139.759719,"level":"chome"},"東和|1":{"lat":35.766717,"lng":139.837455,"level":"chome"},"東和|2":{"lat":35.768887,"lng":139.842158,"level":"chome"},"東和|3":{"lat":35.771514,"lng":139.83793,"level":"chome"},"東和|4":{"lat":35.77316,"lng":139.842109,"level":"chome"},"東和|5":{"lat":35.775458,"lng":139.838452,"level":"chome"},"舎人|1":{"lat":35.807013,"lng":139.770406,"level":"chome"},"舎人|2":{"lat":35.810667,"lng":139.772068,"level":"chome"},"舎人|3":{"lat":35.812852,"lng":139.773788,"level":"chome"},"舎人|4":{"lat":35.816359,"lng":139.768343,"level":"chome"},"舎人|5":{"lat":35.811862,"lng":139.768053,"level":"chome"},"舎人|6":{"lat":35.813131,"lng":139.764084,"level":"chome"},"中川|1":{"lat":35.766434,"lng":139.855348,"level":"chome"},"中川|2":{"lat":35.768939,"lng":139.855403,"level":"chome"},"中川|3":{"lat":35.771204,"lng":139.854021,"level":"chome"},"中川|4":{"lat":35.771552,"lng":139.847137,"level":"chome"},"中川|5":{"lat":35.774721,"lng":139.849604,"level":"chome"},"西綾瀬|1":{"lat":35.76059,"lng":139.816689,"level":"chome"},"西綾瀬|2":{"lat":35.764219,"lng":139.813537,"level":"chome"},"西綾瀬|3":{"lat":35.764097,"lng":139.816804,"level":"chome"},"西綾瀬|4":{"lat":35.765,"lng":139.819672,"level":"chome"},"西伊興町|-":{"lat":35.79365,"lng":139.772641,"level":"town"},"西新井本町|1":{"lat":35.776096,"lng":139.779316,"level":"chome"},"西新井本町|2":{"lat":35.776521,"lng":139.773032,"level":"chome"},"西新井本町|3":{"lat":35.775029,"lng":139.776092,"level":"chome"},"西新井本町|4":{"lat":35.772584,"lng":139.77845,"level":"chome"},"西新井本町|5":{"lat":35.773439,"lng":139.782868,"level":"chome"},"西加平|1":{"lat":35.778968,"lng":139.82272,"level":"chome"},"西加平|2":{"lat":35.780037,"lng":139.819724,"level":"chome"},"西伊興|1":{"lat":35.79165,"lng":139.774614,"level":"chome"},"西伊興|2":{"lat":35.794318,"lng":139.776767,"level":"chome"},"西伊興|3":{"lat":35.798183,"lng":139.777465,"level":"chome"},"西伊興|4":{"lat":35.802297,"lng":139.780809,"level":"chome"},"西新井栄町|1":{"lat":35.774358,"lng":139.789129,"level":"chome"},"西新井栄町|2":{"lat":35.776993,"lng":139.787961,"level":"chome"},"西新井栄町|3":{"lat":35.776457,"lng":139.783479,"level":"chome"},"西新井|1":{"lat":35.780377,"lng":139.781069,"level":"chome"},"西新井|2":{"lat":35.784333,"lng":139.781483,"level":"chome"},"西新井|3":{"lat":35.788145,"lng":139.781453,"level":"chome"},"西新井|4":{"lat":35.788075,"lng":139.775294,"level":"chome"},"西新井|5":{"lat":35.784312,"lng":139.775939,"level":"chome"},"西新井|6":{"lat":35.780561,"lng":139.776121,"level":"chome"},"西新井|7":{"lat":35.78038,"lng":139.771748,"level":"chome"},"西竹の塚|1":{"lat":35.791457,"lng":139.788245,"level":"chome"},"西竹の塚|2":{"lat":35.796214,"lng":139.790174,"level":"chome"},"西保木間|1":{"lat":35.796549,"lng":139.800072,"level":"chome"},"西保木間|2":{"lat":35.80052,"lng":139.799741,"level":"chome"},"西保木間|3":{"lat":35.804364,"lng":139.800014,"level":"chome"},"西保木間|4":{"lat":35.803926,"lng":139.796648,"level":"chome"},"花畑|1":{"lat":35.799674,"lng":139.813241,"level":"chome"},"花畑|2":{"lat":35.802069,"lng":139.8176,"level":"chome"},"花畑|3":{"lat":35.803433,"lng":139.812606,"level":"chome"},"花畑|4":{"lat":35.804047,"lng":139.808069,"level":"chome"},"花畑|5":{"lat":35.80729,"lng":139.808684,"level":"chome"},"花畑|6":{"lat":35.806012,"lng":139.817891,"level":"chome"},"花畑|7":{"lat":35.809394,"lng":139.819203,"level":"chome"},"花畑|8":{"lat":35.812014,"lng":139.822559,"level":"chome"},"東綾瀬|1":{"lat":35.76478,"lng":139.83219,"level":"chome"},"東綾瀬|2":{"lat":35.767642,"lng":139.832498,"level":"chome"},"東綾瀬|3":{"lat":35.770352,"lng":139.833201,"level":"chome"},"東伊興|1":{"lat":35.80335,"lng":139.784066,"level":"chome"},"東伊興|2":{"lat":35.805317,"lng":139.787686,"level":"chome"},"東伊興|3":{"lat":35.801705,"lng":139.791986,"level":"chome"},"東伊興|4":{"lat":35.803309,"lng":139.788359,"level":"chome"},"一ツ家|1":{"lat":35.781424,"lng":139.809811,"level":"chome"},"一ツ家|2":{"lat":35.783263,"lng":139.813407,"level":"chome"},"一ツ家|3":{"lat":35.780181,"lng":139.813468,"level":"chome"},"一ツ家|4":{"lat":35.780427,"lng":139.817171,"level":"chome"},"日ノ出町|-":{"lat":35.751978,"lng":139.809431,"level":"town"},"東保木間|1":{"lat":35.789398,"lng":139.813866,"level":"chome"},"東保木間|2":{"lat":35.792895,"lng":139.813442,"level":"chome"},"平野|1":{"lat":35.78027,"lng":139.806075,"level":"chome"},"平野|2":{"lat":35.783804,"lng":139.804399,"level":"chome"},"平野|3":{"lat":35.784475,"lng":139.807494,"level":"chome"},"東六月町|-":{"lat":35.787585,"lng":139.806056,"level":"town"},"保木間|1":{"lat":35.790517,"lng":139.8065,"level":"chome"},"保木間|2":{"lat":35.79351,"lng":139.806649,"level":"chome"},"保木間|3":{"lat":35.796197,"lng":139.806993,"level":"chome"},"保木間|4":{"lat":35.79882,"lng":139.805606,"level":"chome"},"保木間|5":{"lat":35.80332,"lng":139.803836,"level":"chome"},"保塚町|-":{"lat":35.78636,"lng":139.813008,"level":"town"},"堀之内|1":{"lat":35.774794,"lng":139.755267,"level":"chome"},"堀之内|2":{"lat":35.775859,"lng":139.758014,"level":"chome"},"南花畑|1":{"lat":35.78789,"lng":139.824533,"level":"chome"},"南花畑|2":{"lat":35.790493,"lng":139.819516,"level":"chome"},"南花畑|3":{"lat":35.79195,"lng":139.824844,"level":"chome"},"南花畑|4":{"lat":35.796324,"lng":139.819443,"level":"chome"},"南花畑|5":{"lat":35.796481,"lng":139.814159,"level":"chome"},"宮城|1":{"lat":35.758523,"lng":139.755002,"level":"chome"},"宮城|2":{"lat":35.756421,"lng":139.785732,"level":"chome"},"六木|1":{"lat":35.79112,"lng":139.838618,"level":"chome"},"六木|2":{"lat":35.792453,"lng":139.842482,"level":"chome"},"六木|3":{"lat":35.797191,"lng":139.842365,"level":"chome"},"六木|4":{"lat":35.795681,"lng":139.838422,"level":"chome"},"本木北町|-":{"lat":35.765062,"lng":139.779622,"level":"town"},"本木|1":{"lat":35.761898,"lng":139.785612,"level":"chome"},"本木|2":{"lat":35.766972,"lng":139.784918,"level":"chome"},"本木西町|-":{"lat":35.761619,"lng":139.779323,"level":"town"},"本木東町|-":{"lat":35.766126,"lng":139.782517,"level":"town"},"本木南町|-":{"lat":35.762189,"lng":139.782206,"level":"town"},"谷中|1":{"lat":35.772832,"lng":139.832282,"level":"chome"},"谷中|2":{"lat":35.775982,"lng":139.832902,"level":"chome"},"谷中|3":{"lat":35.779424,"lng":139.835273,"level":"chome"},"谷中|4":{"lat":35.781494,"lng":139.83215,"level":"chome"},"谷中|5":{"lat":35.782777,"lng":139.835094,"level":"chome"},"谷在家|1":{"lat":35.785836,"lng":139.771085,"level":"chome"},"谷在家|2":{"lat":35.784621,"lng":139.767891,"level":"chome"},"谷在家|3":{"lat":35.788335,"lng":139.767783,"level":"chome"},"柳原|1":{"lat":35.745631,"lng":139.813775,"level":"chome"},"柳原|2":{"lat":35.748373,"lng":139.812305,"level":"chome"},"六月|1":{"lat":35.786836,"lng":139.8004,"level":"chome"},"六月|2":{"lat":35.786545,"lng":139.795215,"level":"chome"},"六月|3":{"lat":35.786789,"lng":139.790724,"level":"chome"},"六町|1":{"lat":35.782338,"lng":139.823202,"level":"chome"},"六町|2":{"lat":35.783137,"lng":139.818312,"level":"chome"},"六町|3":{"lat":35.78591,"lng":139.818633,"level":"chome"},"六町|4":{"lat":35.785191,"lng":139.823436,"level":"chome"},"古千谷本町|1":{"lat":35.802426,"lng":139.775171,"level":"chome"},"古千谷本町|2":{"lat":35.805142,"lng":139.775793,"level":"chome"},"古千谷本町|3":{"lat":35.808401,"lng":139.776625,"level":"chome"},"古千谷本町|4":{"lat":35.806387,"lng":139.78039,"level":"chome"},"伊興本町|1":{"lat":35.798405,"lng":139.78777,"level":"chome"},"伊興本町|2":{"lat":35.801059,"lng":139.787634,"level":"chome"},"舎人公園|-":{"lat":35.798275,"lng":139.768267,"level":"town"},"__CITY__|-|-":{"lat":35.77984987313434,"lng":139.79786419776127,"level":"city"}}}