{"meta":{"version":"2025-10-18","jis_muni_code":"11225","name":"入間市"},"data":{"大字扇町屋|-":{"lat":35.82551,"lng":139.397661,"level":"town"},"豊岡|1":{"lat":35.837863,"lng":139.38866,"level":"chome"},"豊岡|2":{"lat":35.835694,"lng":139.384388,"level":"chome"},"豊岡|3":{"lat":35.833981,"lng":139.3882,"level":"chome"},"豊岡|4":{"lat":35.833661,"lng":139.39309,"level":"chome"},"豊岡|5":{"lat":35.835397,"lng":139.394209,"level":"chome"},"扇町屋|1":{"lat":35.831707,"lng":139.386304,"level":"chome"},"扇町屋|2":{"lat":35.833414,"lng":139.38362,"level":"chome"},"扇町屋|3":{"lat":35.830091,"lng":139.38201,"level":"chome"},"扇町屋|4":{"lat":35.828953,"lng":139.384036,"level":"chome"},"扇町屋|5":{"lat":35.827583,"lng":139.380348,"level":"chome"},"大字善蔵新田|-":{"lat":35.820939,"lng":139.387126,"level":"town"},"東町|1":{"lat":35.831906,"lng":139.397596,"level":"chome"},"東町|2":{"lat":35.833446,"lng":139.401505,"level":"chome"},"東町|3":{"lat":35.830492,"lng":139.400987,"level":"chome"},"東町|4":{"lat":35.83262,"lng":139.405011,"level":"chome"},"東町|5":{"lat":35.831019,"lng":139.407536,"level":"chome"},"東町|6":{"lat":35.828633,"lng":139.404082,"level":"chome"},"東町|7":{"lat":35.82749,"lng":139.400457,"level":"chome"},"扇台|1":{"lat":35.831733,"lng":139.392508,"level":"chome"},"扇台|2":{"lat":35.830206,"lng":139.391066,"level":"chome"},"扇台|3":{"lat":35.82872,"lng":139.389264,"level":"chome"},"扇台|4":{"lat":35.827249,"lng":139.388063,"level":"chome"},"扇台|5":{"lat":35.826027,"lng":139.386419,"level":"chome"},"扇台|6":{"lat":35.824595,"lng":139.384623,"level":"chome"},"久保稲荷|1":{"lat":35.828548,"lng":139.395041,"level":"chome"},"久保稲荷|2":{"lat":35.826156,"lng":139.396245,"level":"chome"},"久保稲荷|3":{"lat":35.823455,"lng":139.393017,"level":"chome"},"久保稲荷|4":{"lat":35.824995,"lng":139.390911,"level":"chome"},"久保稲荷|5":{"lat":35.821666,"lng":139.388843,"level":"chome"},"大字黒須|-":{"lat":35.836246,"lng":139.408893,"level":"town"},"黒須|1":{"lat":35.845605,"lng":139.390534,"level":"chome"},"黒須|2":{"lat":35.845964,"lng":139.386306,"level":"chome"},"河原町|-":{"lat":35.842854,"lng":139.38782,"level":"town"},"春日町|1":{"lat":35.848411,"lng":139.379816,"level":"chome"},"春日町|2":{"lat":35.84945,"lng":139.386678,"level":"chome"},"宮前町|-":{"lat":35.845386,"lng":139.380492,"level":"town"},"鍵山|1":{"lat":35.843333,"lng":139.383312,"level":"chome"},"鍵山|2":{"lat":35.843653,"lng":139.3777,"level":"chome"},"鍵山|3":{"lat":35.845224,"lng":139.373999,"level":"chome"},"高倉|1":{"lat":35.838938,"lng":139.384429,"level":"chome"},"高倉|2":{"lat":35.840992,"lng":139.382374,"level":"chome"},"高倉|3":{"lat":35.839617,"lng":139.378594,"level":"chome"},"高倉|4":{"lat":35.83627,"lng":139.380083,"level":"chome"},"高倉|5":{"lat":35.832237,"lng":139.379137,"level":"chome"},"向陽台|1":{"lat":35.840348,"lng":139.392381,"level":"chome"},"向陽台|2":{"lat":35.836532,"lng":139.40115,"level":"chome"},"牛沢町|-":{"lat":35.839848,"lng":139.37282,"level":"town"},"小谷田|1":{"lat":35.822404,"lng":139.381568,"level":"chome"},"小谷田|2":{"lat":35.825114,"lng":139.378218,"level":"chome"},"小谷田|3":{"lat":35.827896,"lng":139.375681,"level":"chome"},"小谷田|4":{"lat":35.824265,"lng":139.374681,"level":"chome"},"上小谷田|1":{"lat":35.830152,"lng":139.373879,"level":"chome"},"上小谷田|2":{"lat":35.833928,"lng":139.374084,"level":"chome"},"上小谷田|3":{"lat":35.831551,"lng":139.370249,"level":"chome"},"森坂|-":{"lat":35.837503,"lng":139.375191,"level":"town"},"大字小谷田|-":{"lat":35.822456,"lng":139.373802,"level":"town"},"大字新久|-":{"lat":35.823443,"lng":139.362064,"level":"town"},"大字狭山ケ原|-":{"lat":35.812759,"lng":139.368356,"level":"town"},"大字木蓮寺|-":{"lat":35.806419,"lng":139.32322,"level":"town"},"大字南峯|-":{"lat":35.810073,"lng":139.327628,"level":"town"},"大字寺竹|-":{"lat":35.811498,"lng":139.334063,"level":"town"},"大字西三ツ木|-":{"lat":35.815942,"lng":139.337499,"level":"town"},"大字上谷ケ貫|-":{"lat":35.815807,"lng":139.342049,"level":"town"},"大字下谷ケ貫|-":{"lat":35.811404,"lng":139.348046,"level":"town"},"大字花ノ木|-":{"lat":35.823281,"lng":139.348766,"level":"town"},"大字中神|-":{"lat":35.817328,"lng":139.354433,"level":"town"},"大字根岸|-":{"lat":35.81855,"lng":139.358157,"level":"town"},"宮寺|-":{"lat":35.793664,"lng":139.379464,"level":"town"},"大字二本木|-":{"lat":35.792802,"lng":139.369127,"level":"town"},"大字狭山台|-":{"lat":35.80238,"lng":139.359227,"level":"town"},"大字上藤沢|-":{"lat":35.813195,"lng":139.390827,"level":"town"},"大字下藤沢|-":{"lat":35.822681,"lng":139.396631,"level":"town"},"東藤沢|1":{"lat":35.824447,"lng":139.413582,"level":"chome"},"東藤沢|2":{"lat":35.82104,"lng":139.416235,"level":"chome"},"東藤沢|3":{"lat":35.81962,"lng":139.414186,"level":"chome"},"東藤沢|4":{"lat":35.817898,"lng":139.417033,"level":"chome"},"東藤沢|5":{"lat":35.815563,"lng":139.415897,"level":"chome"},"東藤沢|6":{"lat":35.815381,"lng":139.412742,"level":"chome"},"東藤沢|7":{"lat":35.814131,"lng":139.409811,"level":"chome"},"東藤沢|8":{"lat":35.812478,"lng":139.40632,"level":"chome"},"大字仏子|-":{"lat":35.83676,"lng":139.357424,"level":"town"},"大字野田|-":{"lat":35.860175,"lng":139.357151,"level":"town"},"大字新光|-":{"lat":35.855507,"lng":139.356125,"level":"town"},"三ツ木台|-":{"lat":35.809963,"lng":139.337753,"level":"town"},"金子中央|-":{"lat":35.814984,"lng":139.331763,"level":"town"},"狭山台|1":{"lat":35.805322,"lng":139.366156,"level":"chome"},"狭山台|2":{"lat":35.804163,"lng":139.362952,"level":"chome"},"狭山台|3":{"lat":35.809618,"lng":139.360537,"level":"chome"},"狭山台|4":{"lat":35.811146,"lng":139.363388,"level":"chome"},"__CITY__|-|-":{"lat":35.825939269230766,"lng":139.3815847788461,"level":"city"}}}