{"meta":{"version":"2025-10-18","jis_muni_code":"14366","name":"開成町"},"data":{"岡野|-":{"lat":35.342395,"lng":139.109815,"level":"town"},"金井島|-":{"lat":35.346749,"lng":139.116645,"level":"town"},"延沢（上延沢）|-":{"lat":35.338721,"lng":139.117925,"level":"town"},"延沢（下延沢）|-":{"lat":35.333506,"lng":139.123727,"level":"town"},"円通寺|-":{"lat":35.333845,"lng":139.118162,"level":"town"},"中之名|-":{"lat":35.330977,"lng":139.119449,"level":"town"},"宮台|-":{"lat":35.325713,"lng":139.122112,"level":"town"},"牛島|-":{"lat":35.319048,"lng":139.131318,"level":"town"},"吉田島（上島）|-":{"lat":35.341511,"lng":139.125601,"level":"town"},"吉田島（河原町）|-":{"lat":35.343024,"lng":139.130073,"level":"town"},"吉田島（榎本）|-":{"lat":35.336166,"lng":139.12917,"level":"town"},"吉田島（中家村）|-":{"lat":35.332353,"lng":139.131718,"level":"town"},"吉田島（下島）|-":{"lat":35.327766,"lng":139.136525,"level":"town"},"みなみ|1":{"lat":35.323348,"lng":139.131207,"level":"chome"},"みなみ|2":{"lat":35.321353,"lng":139.132144,"level":"chome"},"みなみ|3":{"lat":35.320146,"lng":139.12989,"level":"chome"},"みなみ|4":{"lat":35.322274,"lng":139.129286,"level":"chome"},"みなみ|5":{"lat":35.321528,"lng":139.124073,"level":"chome"},"__CITY__|-|-":{"lat":35.329142,"lng":139.12610682608695,"level":"city"}}}