{"meta":{"version":"2025-10-18","jis_muni_code":"12427","name":"長南町"},"data":{"笠森|-":{"lat":35.398106,"lng":140.202564,"level":"town"},"深沢|-":{"lat":35.391663,"lng":140.207626,"level":"town"},"蔵持|-":{"lat":35.382976,"lng":140.214627,"level":"town"},"長南|-":{"lat":35.393754,"lng":140.233518,"level":"town"},"坂本|-":{"lat":35.393197,"lng":140.257975,"level":"town"},"須田|-":{"lat":35.420518,"lng":140.258296,"level":"town"},"米満|-":{"lat":35.414715,"lng":140.249055,"level":"town"},"関原|-":{"lat":35.411271,"lng":140.255364,"level":"town"},"千手堂|-":{"lat":35.406936,"lng":140.246378,"level":"town"},"千田|-":{"lat":35.405676,"lng":140.23273,"level":"town"},"又富|-":{"lat":35.407181,"lng":140.22151,"level":"town"},"棚毛|-":{"lat":35.415119,"lng":140.222418,"level":"town"},"岩川|-":{"lat":35.421932,"lng":140.237343,"level":"town"},"今泉|-":{"lat":35.418957,"lng":140.241436,"level":"town"},"本台|-":{"lat":35.421308,"lng":140.249639,"level":"town"},"上小野田|-":{"lat":35.358389,"lng":140.254734,"level":"town"},"下小野田|-":{"lat":35.369766,"lng":140.259897,"level":"town"},"中原|-":{"lat":35.37967,"lng":140.257995,"level":"town"},"給田|-":{"lat":35.374909,"lng":140.267251,"level":"town"},"小生田|-":{"lat":35.353932,"lng":140.262349,"level":"town"},"地引|-":{"lat":35.367591,"lng":140.272702,"level":"town"},"豊原|-":{"lat":35.378936,"lng":140.283692,"level":"town"},"芝原|-":{"lat":35.366679,"lng":140.291452,"level":"town"},"佐坪|-":{"lat":35.35558,"lng":140.237739,"level":"town"},"市野々|-":{"lat":35.333816,"lng":140.238836,"level":"town"},"山内|-":{"lat":35.343587,"lng":140.219987,"level":"town"},"水沼|-":{"lat":35.361035,"lng":140.218624,"level":"town"},"岩撫|-":{"lat":35.370111,"lng":140.215017,"level":"town"},"竹林|-":{"lat":35.374583,"lng":140.222029,"level":"town"},"茗荷沢|-":{"lat":35.37755,"lng":140.230478,"level":"town"},"小沢|-":{"lat":35.368879,"lng":140.246189,"level":"town"},"報恩寺|-":{"lat":35.379965,"lng":140.244175,"level":"town"},"美原台|-":{"lat":35.363575,"lng":140.251293,"level":"town"},"__CITY__|-|-":{"lat":35.384298848484846,"lng":140.24257327272733,"level":"city"}}}