{"meta":{"version":"2025-10-18","jis_muni_code":"08219","name":"牛久市"},"data":{"牛久町|-":{"lat":35.975754,"lng":140.13676,"level":"town"},"田宮町|-":{"lat":35.976256,"lng":140.133187,"level":"town"},"遠山町|-":{"lat":35.950827,"lng":140.142279,"level":"town"},"庄兵衛新田町|-":{"lat":35.969628,"lng":140.116212,"level":"town"},"新地町|-":{"lat":35.971042,"lng":140.120137,"level":"town"},"上柏田|1":{"lat":35.993876,"lng":140.152914,"level":"chome"},"上柏田|2":{"lat":35.991194,"lng":140.155547,"level":"chome"},"上柏田|3":{"lat":35.990154,"lng":140.160751,"level":"chome"},"上柏田|4":{"lat":35.985768,"lng":140.158212,"level":"chome"},"柏田町|-":{"lat":35.991431,"lng":140.14688,"level":"town"},"猪子町|-":{"lat":35.99828,"lng":140.141945,"level":"town"},"東大和田町|-":{"lat":36.003647,"lng":140.150274,"level":"town"},"中根町|-":{"lat":36.000119,"lng":140.155272,"level":"town"},"東猯穴町|-":{"lat":36.018173,"lng":140.147479,"level":"town"},"下根町|-":{"lat":35.994596,"lng":140.16929,"level":"town"},"岡見町|-":{"lat":35.977117,"lng":140.178082,"level":"town"},"上太田町|-":{"lat":35.960536,"lng":140.189891,"level":"town"},"結束町|-":{"lat":35.964819,"lng":140.177753,"level":"town"},"女化町|-":{"lat":35.951196,"lng":140.175287,"level":"town"},"久野町|-":{"lat":35.969496,"lng":140.223858,"level":"town"},"桂町|-":{"lat":35.975175,"lng":140.243619,"level":"town"},"井ノ岡町|-":{"lat":35.96481,"lng":140.253536,"level":"town"},"奥原町|-":{"lat":35.949736,"lng":140.259028,"level":"town"},"島田町|-":{"lat":35.952379,"lng":140.235513,"level":"town"},"正直町|-":{"lat":35.955441,"lng":140.224174,"level":"town"},"小坂町|-":{"lat":35.96473,"lng":140.205023,"level":"town"},"福田町|-":{"lat":35.973013,"lng":140.19895,"level":"town"},"刈谷町|1":{"lat":35.97465,"lng":140.12763,"level":"chome"},"刈谷町|2":{"lat":35.971476,"lng":140.129425,"level":"chome"},"刈谷町|3":{"lat":35.968594,"lng":140.129395,"level":"chome"},"刈谷町|4":{"lat":35.968335,"lng":140.125085,"level":"chome"},"刈谷町|5":{"lat":35.970983,"lng":140.124736,"level":"chome"},"栄町|1":{"lat":35.988111,"lng":140.14793,"level":"chome"},"栄町|2":{"lat":35.989656,"lng":140.151006,"level":"chome"},"栄町|3":{"lat":35.986777,"lng":140.152027,"level":"chome"},"栄町|4":{"lat":35.983659,"lng":140.15436,"level":"chome"},"栄町|5":{"lat":35.979858,"lng":140.151351,"level":"chome"},"栄町|6":{"lat":35.984341,"lng":140.150254,"level":"chome"},"南|1":{"lat":35.970059,"lng":140.141922,"level":"chome"},"南|2":{"lat":35.973468,"lng":140.146219,"level":"chome"},"南|3":{"lat":35.970945,"lng":140.148181,"level":"chome"},"南|4":{"lat":35.966996,"lng":140.145142,"level":"chome"},"南|5":{"lat":35.965926,"lng":140.149199,"level":"chome"},"南|6":{"lat":35.962148,"lng":140.147545,"level":"chome"},"南|7":{"lat":35.963052,"lng":140.142759,"level":"chome"},"神谷|1":{"lat":35.973362,"lng":140.153086,"level":"chome"},"神谷|2":{"lat":35.968312,"lng":140.154639,"level":"chome"},"神谷|3":{"lat":35.969265,"lng":140.157894,"level":"chome"},"神谷|4":{"lat":35.96562,"lng":140.162365,"level":"chome"},"神谷|5":{"lat":35.964095,"lng":140.158828,"level":"chome"},"神谷|6":{"lat":35.965336,"lng":140.15282,"level":"chome"},"中央|1":{"lat":35.983891,"lng":140.145,"level":"chome"},"中央|2":{"lat":35.982737,"lng":140.147584,"level":"chome"},"中央|3":{"lat":35.978889,"lng":140.146578,"level":"chome"},"中央|4":{"lat":35.976691,"lng":140.148833,"level":"chome"},"中央|5":{"lat":35.977837,"lng":140.142479,"level":"chome"},"さくら台|1":{"lat":35.959708,"lng":140.153463,"level":"chome"},"さくら台|2":{"lat":35.959374,"lng":140.158666,"level":"chome"},"さくら台|3":{"lat":35.959925,"lng":140.162636,"level":"chome"},"さくら台|4":{"lat":35.95996,"lng":140.167914,"level":"chome"},"田宮|2":{"lat":35.985086,"lng":140.142001,"level":"chome"},"田宮|3":{"lat":35.979019,"lng":140.140512,"level":"chome"},"ひたち野東|1":{"lat":36.009448,"lng":140.161132,"level":"chome"},"ひたち野東|2":{"lat":36.00705,"lng":140.167219,"level":"chome"},"ひたち野東|3":{"lat":36.001613,"lng":140.170586,"level":"chome"},"ひたち野東|4":{"lat":36.003451,"lng":140.165933,"level":"chome"},"ひたち野東|5":{"lat":36.004164,"lng":140.159823,"level":"chome"},"ひたち野西|1":{"lat":36.010727,"lng":140.149889,"level":"chome"},"ひたち野西|2":{"lat":36.011049,"lng":140.154597,"level":"chome"},"ひたち野西|3":{"lat":36.010957,"lng":140.157662,"level":"chome"},"ひたち野西|4":{"lat":36.007674,"lng":140.151607,"level":"chome"},"__CITY__|-|-":{"lat":35.97786537662338,"lng":140.15841087012987,"level":"city"}}}